.gitignore
LICENSE
MANIFEST.in
README
setup.py
PyCKLink.egg-info/PKG-INFO
PyCKLink.egg-info/SOURCES.txt
PyCKLink.egg-info/dependency_links.txt
PyCKLink.egg-info/not-zip-safe
PyCKLink.egg-info/top_level.txt
cklink/Target.dll
cklink/Utils.dll
cklink/XmlParser.dll
cklink/__init__.py
cklink/cklink.py
cklink/errors.py
cklink/libScripts.so
cklink/libTarget.so
cklink/libUtils.so
cklink/libXml.so
cklink/libstdc++.so.6
cklink/libusb-1.0.dll
cklink/libusb-1.0.so
cklink/structs.py
cklink/links/CK-Link/Cklink.dll
cklink/links/CK-Link/Legency_ckjaguar.iic
cklink/links/CK-Link/cklink_lite.hex
cklink/links/CK-Link/cklink_lite_iap.hex
cklink/links/CK-Link/cklink_lite_v1.hex
cklink/links/CK-Link/cklink_lite_v1.iic
cklink/links/CK-Link/cklink_pro.bit
cklink/links/CK-Link/cklink_pro.hex
cklink/links/CK-Link/cklink_pro.iic
cklink/links/CK-Link/cklink_v1.bit
cklink/links/CK-Link/cklink_v1.hex
cklink/links/CK-Link/cklink_v1.iic
cklink/links/CK-Link/libCklink.so
cklink/links/Ck-Link/Cklink.dll
cklink/links/Ck-Link/Legency_ckjaguar.iic
cklink/links/Ck-Link/cklink_lite.hex
cklink/links/Ck-Link/cklink_lite_iap.hex
cklink/links/Ck-Link/cklink_lite_v1.hex
cklink/links/Ck-Link/cklink_lite_v1.iic
cklink/links/Ck-Link/cklink_pro.bit
cklink/links/Ck-Link/cklink_pro.hex
cklink/links/Ck-Link/cklink_pro.iic
cklink/links/Ck-Link/cklink_v1.bit
cklink/links/Ck-Link/cklink_v1.hex
cklink/links/Ck-Link/cklink_v1.iic
cklink/links/Ck-Link/libCklink.so
cklink/tdescriptions/c_series/csky-abiv2-c807-tdesc.xml
cklink/tdescriptions/c_series/csky-abiv2-c807f-tdesc.xml
cklink/tdescriptions/c_series/csky-abiv2-c810-tdesc.xml
cklink/tdescriptions/c_series/csky-abiv2-c810t-tdesc.xml
cklink/tdescriptions/c_series/csky-abiv2-c810tv-tdesc.xml
cklink/tdescriptions/c_series/csky-abiv2-c810v-tdesc.xml
cklink/tdescriptions/c_series/csky-abiv2-c860-tdesc.xml
cklink/tdescriptions/c_series/csky-abiv2-c860v-tdesc.xml
cklink/tdescriptions/ck610/csky-abiv1-ck610efm-tdesc.xml
cklink/tdescriptions/ck801/csky-abiv2-ck801-tdesc.xml
cklink/tdescriptions/ck801/csky-abiv2-ck801t-tdesc.xml
cklink/tdescriptions/ck802/csky-abiv2-ck802-tdesc.xml
pycklink.egg-info/PKG-INFO
pycklink.egg-info/SOURCES.txt
pycklink.egg-info/dependency_links.txt
pycklink.egg-info/not-zip-safe
pycklink.egg-info/top_level.txt
