Metadata-Version: 1.2
Name: pycklink
Version: 0.1.1
Summary: Python interface for the T-HEAD CKLink
Home-page: https://pypi.org/project/PyCKLink/
Author: tanjiaxi
Author-email: jxtan@bouffalolab.com
License: MIT
Platform: UNKNOWN
Classifier: Intended Audience :: Developers
Classifier: License :: OSI Approved :: MIT License
Classifier: Operating System :: Microsoft
Classifier: Topic :: Software Development :: Libraries :: Python Modules
Classifier: Programming Language :: Python :: 3
Requires-Python: >3.0,<4.0
